jodev_emailpy/__init__.py
jodev_emailpy/client.py
jodev_emailpy/errors.py
jodev_emailpy/utils.py
jodev_emailpy-0.1.1.dist-info/LICENSE
jodev_emailpy-0.1.1.dist-info/METADATA
jodev_emailpy-0.1.1.dist-info/WHEEL
jodev_emailpy-0.1.1.dist-info/top_level.txt
jodev_emailpy-0.1.1.dist-info/RECORD
