Metadata-Version: 2.1
Name: jodev-emailpy
Version: 0.1.1
Summary: A python library for recieving email directly in your application using emailjs
Home-page: https://github.com/joelwry/jodev_emailpy
Author: joelwry
Author-email: joelwryjolomi@gemail.com
License: MIT
Keywords: emailjs,email,email sender,email reciever
License-File: LICENSE
Requires-Dist: requests
